sample_xblocks/__init__.py
sample_xblocks/basic/__init__.py
sample_xblocks/basic/content.py
sample_xblocks/basic/problem.py
sample_xblocks/basic/slider.py
sample_xblocks/basic/structure.py
sample_xblocks/basic/view_counter.py
sample_xblocks/basic/public/images/correct-icon.png
sample_xblocks/basic/public/images/incorrect-icon.png
sample_xblocks/basic/templates/problem.html
sample_xblocks/basic/templates/sequence.html
sample_xblocks/basic/templates/vertical.html
sample_xblocks/filethumbs/__init__.py
sample_xblocks/filethumbs/filethumbs.py
sample_xblocks/filethumbs/static/README.md
sample_xblocks/filethumbs/static/css/thumbs.css
sample_xblocks/filethumbs/static/html/thumbs.html
sample_xblocks/filethumbs/static/js/README.md
sample_xblocks/filethumbs/static/js/SpecRunner.html
sample_xblocks/filethumbs/static/js/lib/jasmine-jquery.js
sample_xblocks/filethumbs/static/js/lib/jquery-1.9.1.min.js
sample_xblocks/filethumbs/static/js/lib/jasmine-1.3.1/MIT.LICENSE
sample_xblocks/filethumbs/static/js/lib/jasmine-1.3.1/jasmine-html.js
sample_xblocks/filethumbs/static/js/lib/jasmine-1.3.1/jasmine.css
sample_xblocks/filethumbs/static/js/lib/jasmine-1.3.1/jasmine.js
sample_xblocks/filethumbs/static/js/spec/thumbs_spec.js
sample_xblocks/filethumbs/static/js/src/thumbs.js
sample_xblocks/thumbs/__init__.py
sample_xblocks/thumbs/thumbs.py
sample_xblocks/thumbs/static/README.md
sample_xblocks/thumbs/static/css/thumbs.css
sample_xblocks/thumbs/static/html/thumbs.html
sample_xblocks/thumbs/static/js/README.md
sample_xblocks/thumbs/static/js/SpecRunner.html
sample_xblocks/thumbs/static/js/lib/jasmine-jquery.js
sample_xblocks/thumbs/static/js/lib/jquery-1.9.1.min.js
sample_xblocks/thumbs/static/js/lib/jasmine-1.3.1/MIT.LICENSE
sample_xblocks/thumbs/static/js/lib/jasmine-1.3.1/jasmine-html.js
sample_xblocks/thumbs/static/js/lib/jasmine-1.3.1/jasmine.css
sample_xblocks/thumbs/static/js/lib/jasmine-1.3.1/jasmine.js
sample_xblocks/thumbs/static/js/spec/thumbs_spec.js
xblock_sdk-0.13.0.dist-info/licenses/LICENSE.TXT
xblock_sdk-0.13.0.dist-info/METADATA
xblock_sdk-0.13.0.dist-info/WHEEL
xblock_sdk-0.13.0.dist-info/entry_points.txt
xblock_sdk-0.13.0.dist-info/top_level.txt
xblock_sdk-0.13.0.dist-info/RECORD
