Metadata-Version: 2.4
Name: xblock-sdk
Version: 0.13.0
Summary: XBlock SDK
Classifier: Development Status :: 3 - Alpha
Classifier: Framework :: Django
Classifier: Framework :: Django :: 4.2
Classifier: Framework :: Django :: 5.2
Classifier: Intended Audience :: Developers
Classifier: License :: OSI Approved :: GNU Affero General Public License v3 or later (AGPLv3+)
Classifier: Natural Language :: English
Classifier: Programming Language :: Python :: 3
Classifier: Programming Language :: Python :: 3.11
Classifier: Programming Language :: Python :: 3.12
License-File: LICENSE.TXT
Requires-Dist: Django
Requires-Dist: XBlock
Requires-Dist: cookiecutter
Requires-Dist: fs-s3fs
Requires-Dist: lxml
Requires-Dist: pypng
Requires-Dist: requests
Requires-Dist: simplejson
Requires-Dist: web-fragments
Requires-Dist: webob
Dynamic: classifier
Dynamic: description
Dynamic: license-file
Dynamic: requires-dist
Dynamic: summary
